LICENSE
README.md
setup.py
swagger2/__init__.py
swagger2/loader.py
swagger2/swagger.py
swagger2/utils.py
swagger2.egg-info/PKG-INFO
swagger2.egg-info/SOURCES.txt
swagger2.egg-info/dependency_links.txt
swagger2.egg-info/requires.txt
swagger2.egg-info/top_level.txt