Metadata-Version: 2.1
Name: swagger2
Version: 0.0.6
Summary: 实现了Swagger文档生成Python请求数据功能，借助主流测试框架可快速完成大批量的接口测试任务。
Home-page: https://github.com/JingheLee/swagger2
Author: Jinghe Lee
Author-email: jinghe_lee@163.com
License: UNKNOWN
Platform: UNKNOWN
License-File: LICENSE
